tahdig/__init__.py
tahdig/config.py
tahdig/constants.py
tahdig/debug.py
tahdig/exceptions.py
tahdig/registry.py
tahdig/debug_tools/__init__.py
tahdig/debug_tools/analyzers.py
tahdig/debug_tools/generators.py
tahdig/debug_tools/linters.py
tahdig/debug_tools/validators.py
tahdig/debug_tools/visualizers.py
tahdig-0.0.3.dist-info/licenses/LICENSE
tahdig-0.0.3.dist-info/METADATA
tahdig-0.0.3.dist-info/WHEEL
tahdig-0.0.3.dist-info/top_level.txt
tahdig-0.0.3.dist-info/RECORD
