Metadata-Version: 2.4
Name: tahdig
Version: 0.0.3
Summary: Configuration with a crispy layer - A delightful Python configuration management system
Author-email: Fardin <fardin.ayar@aut.ac.ir>, Ali <ali.sheykh@aut.ac.ir>
License: MIT
Project-URL: Homepage, https://github.com/fardin/tahdig
Project-URL: Documentation, https://tahdig.readthedocs.io
Project-URL: Repository, https://github.com/fardin/tahdig
Project-URL: Bug Tracker, https://github.com/fardin/tahdig/issues
Keywords: configuration,config,settings,registry,yaml,json
Classifier: Development Status :: 5 - Production/Stable
Classifier: Intended Audience :: Developers
Classifier: License :: OSI Approved :: MIT License
Classifier: Programming Language :: Python :: 3
Classifier: Programming Language :: Python :: 3.7
Classifier: Programming Language :: Python :: 3.8
Classifier: Programming Language :: Python :: 3.9
Classifier: Programming Language :: Python :: 3.10
Classifier: Programming Language :: Python :: 3.11
Classifier: Topic :: Software Development :: Libraries :: Python Modules
Classifier: Topic :: Utilities
Requires-Python: >=3.7
License-File: LICENSE
Requires-Dist: pyyaml>=5.1
Provides-Extra: dev
Requires-Dist: pytest>=7.0; extra == "dev"
Requires-Dist: pytest-cov>=4.0; extra == "dev"
Requires-Dist: black>=22.0; extra == "dev"
Requires-Dist: flake8>=5.0; extra == "dev"
Requires-Dist: mypy>=0.990; extra == "dev"
Provides-Extra: profiling
Requires-Dist: psutil>=5.8; extra == "profiling"
Provides-Extra: watch
Requires-Dist: watchdog>=2.0; extra == "watch"
Dynamic: license-file
